{"id":18651,"date":"2021-04-21T06:02:47","date_gmt":"2021-04-21T06:02:47","guid":{"rendered":"https:\/\/www.testingxperts.com\/?page_id=18651"},"modified":"2023-10-13T10:11:08","modified_gmt":"2023-10-13T10:11:08","slug":"test-automation-in-devops-gb-en","status":"publish","type":"page","link":"https:\/\/www.testingxperts.com\/services\/test-automation-in-devops\/gb-en","title":{"rendered":"Test Automation in DevOps UK"},"content":{"rendered":"","protected":false},"excerpt":{"rendered":"","protected":false},"author":6,"featured_media":0,"parent":16959,"menu_order":0,"comment_status":"closed","ping_status":"closed","template":"templates-pages\/Test-Automation-in-Devops-gb-en.php","meta":{"om_disable_all_campaigns":false,"_lmt_disableupdate":"no","_lmt_disable":"","_mi_skip_tracking":false},"aioseo_notices":[],"_links":{"self":[{"href":"https:\/\/www.testingxperts.com\/wp-json\/wp\/v2\/pages\/18651"}],"collection":[{"href":"https:\/\/www.testingxperts.com\/wp-json\/wp\/v2\/pages"}],"about":[{"href":"https:\/\/www.testingxperts.com\/wp-json\/wp\/v2\/types\/page"}],"author":[{"embeddable":true,"href":"https:\/\/www.testingxperts.com\/wp-json\/wp\/v2\/users\/6"}],"replies":[{"embeddable":true,"href":"https:\/\/www.testingxperts.com\/wp-json\/wp\/v2\/comments?post=18651"}],"version-history":[{"count":8,"href":"https:\/\/www.testingxperts.com\/wp-json\/wp\/v2\/pages\/18651\/revisions"}],"predecessor-version":[{"id":29604,"href":"https:\/\/www.testingxperts.com\/wp-json\/wp\/v2\/pages\/18651\/revisions\/29604"}],"up":[{"embeddable":true,"href":"https:\/\/www.testingxperts.com\/wp-json\/wp\/v2\/pages\/16959"}],"wp:attachment":[{"href":"https:\/\/www.testingxperts.com\/wp-json\/wp\/v2\/media?parent=18651"}],"curies":[{"name":"wp","href":"https:\/\/api.w.org\/{rel}","templated":true}]}}