{"id":264,"date":"2019-02-15T09:36:28","date_gmt":"2019-02-15T09:36:28","guid":{"rendered":"https:\/\/www.testingxperts.com\/?page_id=264"},"modified":"2023-09-21T10:30:55","modified_gmt":"2023-09-21T10:30:55","slug":"media-and-publishing","status":"publish","type":"page","link":"https:\/\/www.testingxperts.com\/industries\/media-and-publishing\/","title":{"rendered":"Media and Publishing"},"content":{"rendered":"","protected":false},"excerpt":{"rendered":"","protected":false},"author":6,"featured_media":2535,"parent":2771,"menu_order":0,"comment_status":"closed","ping_status":"closed","template":"templates-pages\/media-and-publishing.php","meta":{"om_disable_all_campaigns":false,"_lmt_disableupdate":"no","_lmt_disable":"","_mi_skip_tracking":false},"aioseo_notices":[],"_links":{"self":[{"href":"https:\/\/www.testingxperts.com\/wp-json\/wp\/v2\/pages\/264"}],"collection":[{"href":"https:\/\/www.testingxperts.com\/wp-json\/wp\/v2\/pages"}],"about":[{"href":"https:\/\/www.testingxperts.com\/wp-json\/wp\/v2\/types\/page"}],"author":[{"embeddable":true,"href":"https:\/\/www.testingxperts.com\/wp-json\/wp\/v2\/users\/6"}],"replies":[{"embeddable":true,"href":"https:\/\/www.testingxperts.com\/wp-json\/wp\/v2\/comments?post=264"}],"version-history":[{"count":5,"href":"https:\/\/www.testingxperts.com\/wp-json\/wp\/v2\/pages\/264\/revisions"}],"predecessor-version":[{"id":29095,"href":"https:\/\/www.testingxperts.com\/wp-json\/wp\/v2\/pages\/264\/revisions\/29095"}],"up":[{"embeddable":true,"href":"https:\/\/www.testingxperts.com\/wp-json\/wp\/v2\/pages\/2771"}],"wp:featuredmedia":[{"embeddable":true,"href":"https:\/\/www.testingxperts.com\/wp-json\/wp\/v2\/media\/2535"}],"wp:attachment":[{"href":"https:\/\/www.testingxperts.com\/wp-json\/wp\/v2\/media?parent=264"}],"curies":[{"name":"wp","href":"https:\/\/api.w.org\/{rel}","templated":true}]}}