{"id":28850,"date":"2023-05-24T16:17:12","date_gmt":"2023-05-24T16:17:12","guid":{"rendered":"https:\/\/www.testingxperts.com\/?p=28850"},"modified":"2023-05-25T06:41:26","modified_gmt":"2023-05-25T06:41:26","slug":"evolution-of-software-testing","status":"publish","type":"post","link":"https:\/\/www.testingxperts.com\/blog\/evolution-of-software-testing","title":{"rendered":"Evolution Of Software Testing"},"content":{"rendered":"<p>Software Testing methodologies have come a long way over the years, adapting to the ever-evolving landscape of technology and software development. From manual testing to automated frameworks, the journey of testing has witnessed remarkable transformations, shaping the way we ensure the quality and reliability of our digital products. In this captivating infographic, we delve into the Evolution of Testing, tracing the key milestones, methodologies, and tools that have revolutionized the testing landscape.<\/p>\r\n\r\n<p><center><img src=\"https:\/\/www.testingxperts.com\/wp-content\/uploads\/2023\/05\/Evolution-of-Software-Testing-2.jpg\" alt=\"Evolution of Software Testing\" width=\"1400\" height=\"4700\" class=\"alignnone size-full wp-image-28852\" \/><\/center><\/p>","protected":false},"excerpt":{"rendered":"<p>The evolution of testing methodologies has been a fascinating journey, driven by the need for efficient and effective ways to ensure the quality of software and digital products. From the early days of manual testing, where every aspect was meticulously checked by human testers, to the rise of automated testing frameworks that brought speed and repeatability to the process, testing has constantly evolved to keep pace with the demands of an ever-changing technology landscape. This infographic is a brief exploration of the key milestones and transformations that have shaped the evolution of testing, showcasing how advancements in types of testing. <\/p>\n","protected":false},"author":5,"featured_media":28851,"comment_status":"open","ping_status":"open","sticky":false,"template":"","format":"standard","meta":{"om_disable_all_campaigns":false,"_lmt_disableupdate":"","_lmt_disable":"","_mi_skip_tracking":false},"categories":[248],"tags":[],"aioseo_notices":[],"modified_by":"sitemanager","_links":{"self":[{"href":"https:\/\/www.testingxperts.com\/wp-json\/wp\/v2\/posts\/28850"}],"collection":[{"href":"https:\/\/www.testingxperts.com\/wp-json\/wp\/v2\/posts"}],"about":[{"href":"https:\/\/www.testingxperts.com\/wp-json\/wp\/v2\/types\/post"}],"author":[{"embeddable":true,"href":"https:\/\/www.testingxperts.com\/wp-json\/wp\/v2\/users\/5"}],"replies":[{"embeddable":true,"href":"https:\/\/www.testingxperts.com\/wp-json\/wp\/v2\/comments?post=28850"}],"version-history":[{"count":25,"href":"https:\/\/www.testingxperts.com\/wp-json\/wp\/v2\/posts\/28850\/revisions"}],"predecessor-version":[{"id":28881,"href":"https:\/\/www.testingxperts.com\/wp-json\/wp\/v2\/posts\/28850\/revisions\/28881"}],"wp:featuredmedia":[{"embeddable":true,"href":"https:\/\/www.testingxperts.com\/wp-json\/wp\/v2\/media\/28851"}],"wp:attachment":[{"href":"https:\/\/www.testingxperts.com\/wp-json\/wp\/v2\/media?parent=28850"}],"wp:term":[{"taxonomy":"category","embeddable":true,"href":"https:\/\/www.testingxperts.com\/wp-json\/wp\/v2\/categories?post=28850"},{"taxonomy":"post_tag","embeddable":true,"href":"https:\/\/www.testingxperts.com\/wp-json\/wp\/v2\/tags?post=28850"}],"curies":[{"name":"wp","href":"https:\/\/api.w.org\/{rel}","templated":true}]}}